cov_change/__init__.py
cov_change/cov_change_check.py
cov_change/coverage_parser.py
cov_change/diff_parser.py
cov_change/main.py
cov_change/output_writer.py
cov_change/utils.py
cov_change-0.1.4.dist-info/LICENSE
cov_change-0.1.4.dist-info/METADATA
cov_change-0.1.4.dist-info/WHEEL
cov_change-0.1.4.dist-info/entry_points.txt
cov_change-0.1.4.dist-info/RECORD
