Metadata-Version: 2.1
Name: cov-change
Version: 0.1.4
Summary: A tool to help you find the changes in your code that are not covered by your tests
Home-page: https://pypi.org/project/cov-change/
License: MIT
Author: vsingh18567
Author-email: vsingh18567@gmail.com
Requires-Python: >=3.10,<4.0
Classifier: License :: OSI Approved :: MIT License
Classifier: Programming Language :: Python :: 3
Classifier: Programming Language :: Python :: 3.10
Classifier: Programming Language :: Python :: 3.11
Requires-Dist: dacite (>=1.8.1,<2.0.0)
Requires-Dist: rich (>=13.6.0,<14.0.0)
Project-URL: Repository, https://github.com/vsingh18567/cov-change
